hyperboard/__init__.py
hyperboard/agent.py
hyperboard/hyperboard_run.py
hyperboard/recorder.py
hyperboard/server.py
hyperboard/static/css/bootstrap-table.min.css
hyperboard/static/css/bootstrap-theme.min.css
hyperboard/static/css/bootstrap.min.css
hyperboard/static/css/curve.css
hyperboard/static/css/multiple-select.css
hyperboard/static/css/multiple-select.png
hyperboard/static/fonts/glyphicons-halflings-regular.eot
hyperboard/static/fonts/glyphicons-halflings-regular.svg
hyperboard/static/fonts/glyphicons-halflings-regular.ttf
hyperboard/static/fonts/glyphicons-halflings-regular.woff
hyperboard/static/fonts/glyphicons-halflings-regular.woff2
hyperboard/static/js/bootstrap-table.min.js
hyperboard/static/js/bootstrap.min.js
hyperboard/static/js/curve.js
hyperboard/static/js/d3.v4.min.js
hyperboard/static/js/jquery-3.1.1.min.js
hyperboard/static/js/multiple-select.js
hyperboard/templates/curve.html
hyperboard-0.1.1.dist-info/DESCRIPTION.rst
hyperboard-0.1.1.dist-info/METADATA
hyperboard-0.1.1.dist-info/RECORD
hyperboard-0.1.1.dist-info/WHEEL
hyperboard-0.1.1.dist-info/entry_points.txt
hyperboard-0.1.1.dist-info/metadata.json
hyperboard-0.1.1.dist-info/top_level.txt
